gino_sanic.py
gino_sanic-0.1.0.dist-info/entry_points.txt
gino_sanic-0.1.0.dist-info/LICENSE
gino_sanic-0.1.0.dist-info/WHEEL
gino_sanic-0.1.0.dist-info/METADATA
gino_sanic-0.1.0.dist-info/RECORD
